odoo/addons/web_widget_mpld3_chart/README.rst
odoo/addons/web_widget_mpld3_chart/__init__.py
odoo/addons/web_widget_mpld3_chart/__manifest__.py
odoo/addons/web_widget_mpld3_chart/i18n/ca.po
odoo/addons/web_widget_mpld3_chart/i18n/es.po
odoo/addons/web_widget_mpld3_chart/i18n/pt_BR.po
odoo/addons/web_widget_mpld3_chart/i18n/web_widget_mpld3_chart.pot
odoo/addons/web_widget_mpld3_chart/readme/CONTRIBUTORS.rst
odoo/addons/web_widget_mpld3_chart/readme/CREDITS.rst
odoo/addons/web_widget_mpld3_chart/readme/DESCRIPTION.rst
odoo/addons/web_widget_mpld3_chart/readme/INSTALL.rst
odoo/addons/web_widget_mpld3_chart/readme/USAGE.rst
odoo/addons/web_widget_mpld3_chart/static/description/icon.png
odoo/addons/web_widget_mpld3_chart/static/description/index.html
odoo/addons/web_widget_mpld3_chart/static/src/js/web_widget_mpld3_chart.js
odoo/addons/web_widget_mpld3_chart/static/src/lib/d3/d3.v3.min.js
odoo/addons/web_widget_mpld3_chart/static/src/lib/mpld3/mpld3.v0.3.1.dev1.js
odoo/addons/web_widget_mpld3_chart/views/web_widget_mpld3_chart.xml
odoo12_addon_web_widget_mpld3_chart-12.0.1.0.0.99.dev10.dist-info/METADATA
odoo12_addon_web_widget_mpld3_chart-12.0.1.0.0.99.dev10.dist-info/WHEEL
odoo12_addon_web_widget_mpld3_chart-12.0.1.0.0.99.dev10.dist-info/top_level.txt
odoo12_addon_web_widget_mpld3_chart-12.0.1.0.0.99.dev10.dist-info/RECORD
